dissect/esedb/__init__.py
dissect/esedb/btree.py
dissect/esedb/c_esedb.py
dissect/esedb/compression.py
dissect/esedb/cursor.py
dissect/esedb/esedb.py
dissect/esedb/exceptions.py
dissect/esedb/index.py
dissect/esedb/lcmapstring.py
dissect/esedb/page.py
dissect/esedb/record.py
dissect/esedb/sorting_table.py
dissect/esedb/table.py
dissect/esedb/tools/__init__.py
dissect/esedb/tools/impacket.py
dissect/esedb/tools/sru.py
dissect/esedb/tools/ual.py
dissect_esedb-3.17.dist-info/licenses/COPYRIGHT
dissect_esedb-3.17.dist-info/licenses/LICENSE
dissect_esedb-3.17.dist-info/METADATA
dissect_esedb-3.17.dist-info/WHEEL
dissect_esedb-3.17.dist-info/top_level.txt
dissect_esedb-3.17.dist-info/RECORD
